MLpkgMA/ComprehensibilityAnalysis.py
MLpkgMA/ConcreteML_Class.py
MLpkgMA/FunctionalityAnalysis.py
MLpkgMA/Interface.py
MLpkgMA/__init__.py
MLpkgMA-0.0.1.dist-info/LICENSE
MLpkgMA-0.0.1.dist-info/METADATA
MLpkgMA-0.0.1.dist-info/WHEEL
MLpkgMA-0.0.1.dist-info/top_level.txt
MLpkgMA-0.0.1.dist-info/RECORD
