Metadata-Version: 2.1
Name: MLpkgMA
Version: 0.0.1
Summary: A small package for quality analysis of machine learning models
Home-page: https://github.com/DahitoMA/Coding_challenge
Author: Marie-Ange Dahito
Author-email: firstname.lastname@inria.fr
License: UNKNOWN
Platform: UNKNOWN
Classifier: Programming Language :: Python :: 3
Classifier: License :: OSI Approved :: MIT License
Classifier: Operating System :: OS Independent
Requires-Python: >=3.7
